type_preserving_scaler/__init__.py
type_preserving_scaler-0.0.1.dist-info/LICENSE
type_preserving_scaler-0.0.1.dist-info/METADATA
type_preserving_scaler-0.0.1.dist-info/WHEEL
type_preserving_scaler-0.0.1.dist-info/top_level.txt
type_preserving_scaler-0.0.1.dist-info/RECORD
